linknlink/__init__.py
linknlink/const.py
linknlink/device.py
linknlink/exceptions.py
linknlink/protocol.py
linknlink/remote.py
linknlink/sensor.py
linknlink-0.2.4.dist-info/LICENSE
linknlink-0.2.4.dist-info/METADATA
linknlink-0.2.4.dist-info/WHEEL
linknlink-0.2.4.dist-info/top_level.txt
linknlink-0.2.4.dist-info/RECORD
